coord/__init__.py
coord/_version.py
coord/angle.py
coord/angleunit.py
coord/celestial.py
coord/util.py
LSSTDESC.Coord-1.3.0.dist-info/LICENSE
LSSTDESC.Coord-1.3.0.dist-info/METADATA
LSSTDESC.Coord-1.3.0.dist-info/WHEEL
LSSTDESC.Coord-1.3.0.dist-info/top_level.txt
LSSTDESC.Coord-1.3.0.dist-info/RECORD
