Metadata-Version: 2.1
Name: LSSTDESC.Coord
Version: 1.3.0
Summary: Python module for handling angles and celestial coordinates
Home-page: https://github.com/LSSTDESC/Coord
Download-URL: https://github.com/LSSTDESC/Coord/releases/tag/v1.3.0.zip
Author: LSST DESC (contact: Mike Jarvis)
Author-email: michael@jarvis.net
License: MIT License
License-File: LICENSE
Requires-Dist: numpy
Requires-Dist: future
